{"name":"Como usuario de Nomicol quiero registrar una nueva empresa","id":"registrar-empresa;como-usuario-de-nomicol-quiero-registrar-una-nueva-empresa","testSteps":[{"number":1,"description":"Given el usuario ingresa a la pagina de Nomicol","duration":2918,"startTime":"2022-04-27T11:27:27.785-05:00[America/Bogota]","screenshots":[{"screenshot":"0506a3a1dbbee2235fe47286b51a09f8232743f85c8d1caad92c55e9d4d990ac.png","timeStamp":1651076850702}],"result":"SUCCESS","precondition":false,"level":0},{"number":2,"description":"When el usuario  hace clic en Registrate","duration":38,"startTime":"2022-04-27T11:27:30.705-05:00[America/Bogota]","screenshots":[{"screenshot":"0506a3a1dbbee2235fe47286b51a09f8232743f85c8d1caad92c55e9d4d990ac.png","htmlSource":"pagesource2182234997793805155.html.txt","timeStamp":1651076850741}],"exception":{"errorType":"java.lang.NullPointerException","stackTrace":[{"declaringClass":"Tests.NomicolTest","methodName":"clicEnRegistrate","fileName":"NomicolTest.java","lineNumber":15},{"declaringClass":"Definitions.NomicolDefinitions","methodName":"elUsuarioHaceClicEnRegistrate","fileName":"NomicolDefinitions.java","lineNumber":20},{"declaringClass":"✽","methodName":"el usuario  hace clic en Registrate","fileName":"src/test/resources/features/NomicolAutomation.feature","lineNumber":6}]},"result":"ERROR","precondition":false,"level":0},{"number":3,"description":"And el usuario diligencia el formulario de Empieza Ahora","duration":1,"startTime":"2022-04-27T11:27:30.743-05:00[America/Bogota]","result":"SKIPPED","precondition":false,"level":0},{"number":4,"description":"And el usuario hace clic en el boton  Continuar","duration":1,"startTime":"2022-04-27T11:27:30.744-05:00[America/Bogota]","result":"SKIPPED","precondition":false,"level":0},{"number":5,"description":"And el usuario diligencia el segundo formulario de registro","duration":1,"startTime":"2022-04-27T11:27:30.745-05:00[America/Bogota]","result":"SKIPPED","precondition":false,"level":0},{"number":6,"description":"And el usuario hace clic en el boton  Crear Cuenta","duration":1,"startTime":"2022-04-27T11:27:30.746-05:00[America/Bogota]","result":"SKIPPED","precondition":false,"level":0},{"number":7,"description":"When el usuario confirma su correo electronico","duration":1,"startTime":"2022-04-27T11:27:30.747-05:00[America/Bogota]","result":"SKIPPED","precondition":false,"level":0},{"number":8,"description":"And el Usuario termina el proceso de registro de su empresa","duration":1,"startTime":"2022-04-27T11:27:30.748-05:00[America/Bogota]","result":"SKIPPED","precondition":false,"level":0},{"number":9,"description":"Then el usuario puede ingresar a su empresa","duration":1,"startTime":"2022-04-27T11:27:30.749-05:00[America/Bogota]","result":"SKIPPED","precondition":false,"level":0}],"userStory":{"id":"registrar-empresa","storyName":"Registrar empresa","path":"src/test/resources/features/NomicolAutomation.feature","type":"feature"},"featureTag":{"name":"Features/Registrar empresa","type":"feature","displayName":"Features/Registrar empresa"},"title":"Como usuario de Nomicol quiero registrar una nueva empresa","tags":[{"name":"Registrar empresa","type":"feature","displayName":"Registrar empresa"},{"name":"RegistrarEmpresa","type":"tag","displayName":"RegistrarEmpresa"}],"startTime":"2022-04-27T11:27:27.723-05:00[America/Bogota]","duration":4088,"testFailureCause":{"errorType":"java.lang.NullPointerException","stackTrace":[{"declaringClass":"Tests.NomicolTest","methodName":"clicEnRegistrate","fileName":"NomicolTest.java","lineNumber":15},{"declaringClass":"Definitions.NomicolDefinitions","methodName":"elUsuarioHaceClicEnRegistrate","fileName":"NomicolDefinitions.java","lineNumber":20},{"declaringClass":"✽","methodName":"el usuario  hace clic en Registrate","fileName":"src/test/resources/features/NomicolAutomation.feature","lineNumber":6}]},"testFailureClassname":"java.lang.NullPointerException","testFailureSummary":"ERROR;java.lang.NullPointerException;null;NomicolTest.java","projectKey":"","annotatedResult":"ERROR","sessionId":"47a0c555ad81970fe6b7460639b1bbc6","driver":"chrome","manual":false,"testSource":"Cucumber","result":"ERROR"}